MANIFEST.in
README.txt
plonetheme.Bangalore-configure.zcml
setup.cfg
setup.py
docs/HISTORY.txt
docs/INSTALL.txt
docs/LICENSE.GPL
docs/LICENSE.txt
plonetheme/__init__.py
plonetheme.Bangalore.egg-info/PKG-INFO
plonetheme.Bangalore.egg-info/SOURCES.txt
plonetheme.Bangalore.egg-info/dependency_links.txt
plonetheme.Bangalore.egg-info/entry_points.txt
plonetheme.Bangalore.egg-info/namespace_packages.txt
plonetheme.Bangalore.egg-info/not-zip-safe
plonetheme.Bangalore.egg-info/paster_plugins.txt
plonetheme.Bangalore.egg-info/requires.txt
plonetheme.Bangalore.egg-info/top_level.txt
plonetheme/Bangalore/__init__.py
plonetheme/Bangalore/configure.zcml
plonetheme/Bangalore/licensinginfo.txt
plonetheme/Bangalore/profiles.zcml
plonetheme/Bangalore/setuphandlers.py
plonetheme/Bangalore/skins.zcml
plonetheme/Bangalore/tests.py
plonetheme/Bangalore/version.txt
plonetheme/Bangalore/browser/Bangalore.py
plonetheme/Bangalore/browser/__init__.py
plonetheme/Bangalore/browser/configure.zcml
plonetheme/Bangalore/browser/interfaces.py
plonetheme/Bangalore/browser/viewlet.pt
plonetheme/Bangalore/browser/viewlets.pt
plonetheme/Bangalore/browser/viewlets.py
plonetheme/Bangalore/browser/images/README.txt
plonetheme/Bangalore/browser/images/bgl_bottom.jpg
plonetheme/Bangalore/browser/images/bgl_horizontal_bg.jpg
plonetheme/Bangalore/browser/images/bgl_search_button.jpg
plonetheme/Bangalore/browser/stylesheets/README.txt
plonetheme/Bangalore/browser/stylesheets/main.css
plonetheme/Bangalore/browser/templates/bgl_path_bar.pt
plonetheme/Bangalore/browser/templates/favicon.pt
plonetheme/Bangalore/browser/templates/search_portlet.pt
plonetheme/Bangalore/browser/templates/site_actions_footer.pt
plonetheme/Bangalore/profiles/default/cssregistry.xml
plonetheme/Bangalore/profiles/default/jsregistry.xml
plonetheme/Bangalore/profiles/default/metadata.xml
plonetheme/Bangalore/profiles/default/plonetheme.Bangalore_various.txt
plonetheme/Bangalore/profiles/default/portlets.xml
plonetheme/Bangalore/profiles/default/skins.xml
plonetheme/Bangalore/profiles/default/viewlets.xml
plonetheme/Bangalore/skins/plonetheme_Bangalore_custom_images/CONTENT.txt
plonetheme/Bangalore/skins/plonetheme_Bangalore_custom_images/bullet.gif
plonetheme/Bangalore/skins/plonetheme_Bangalore_custom_images/bulletBig.gif
plonetheme/Bangalore/skins/plonetheme_Bangalore_custom_images/bullet_icon.gif
